poma/__init__.py
poma/client.py
poma/exceptions.py
poma/retrieval.py
poma/integrations/__init__.py
poma/integrations/langchain_poma.py
poma/integrations/llamaindex_poma.py
poma-0.2.3.dist-info/licenses/LICENSE
poma-0.2.3.dist-info/METADATA
poma-0.2.3.dist-info/WHEEL
poma-0.2.3.dist-info/top_level.txt
poma-0.2.3.dist-info/RECORD
