Metadata-Version: 2.4
Name: poma
Version: 0.2.3
Summary: Official Python SDK for the Poma document-processing API
Author-email: "POMA AI GmbH, Berlin" <sdk@poma-ai.com>
License-Expression: MPL-2.0
Keywords: chunking,structure,rag,poma,documents,ai
Requires-Python: >=3.10
License-File: LICENSE
Requires-Dist: httpx==0.28.1
Requires-Dist: pydantic==2.11.7
Provides-Extra: integrations
Requires-Dist: langchain==0.3.27; extra == "integrations"
Requires-Dist: langchain-text-splitters==0.3.9; extra == "integrations"
Requires-Dist: llama-index==0.13.0; extra == "integrations"
Provides-Extra: integration-examples
Requires-Dist: langchain==0.3.27; extra == "integration-examples"
Requires-Dist: langchain-text-splitters==0.3.9; extra == "integration-examples"
Requires-Dist: llama-index==0.13.0; extra == "integration-examples"
Requires-Dist: llama-index-vector-stores-faiss==0.5.0; extra == "integration-examples"
Requires-Dist: faiss-cpu==1.10.0; extra == "integration-examples"
Requires-Dist: langchain_openai==0.3.28; extra == "integration-examples"
Requires-Dist: langchain_community==0.3.27; extra == "integration-examples"
Requires-Dist: llama-index-embeddings-langchain==0.4.0; extra == "integration-examples"
Requires-Dist: dotenv; extra == "integration-examples"
Dynamic: license-file
